usdm4_excel/__info__.py
usdm4_excel/__init__.py
usdm4_excel/export/__init__.py
usdm4_excel/export/base/__init__.py
usdm4_excel/export/base/base_panel.py
usdm4_excel/export/base/base_sheet.py
usdm4_excel/export/base/collection_panel.py
usdm4_excel/export/base/ct_version.py
usdm4_excel/export/base/empty_sheet.py
usdm4_excel/export/configuration_sheet/__init__.py
usdm4_excel/export/configuration_sheet/configuration_panel.py
usdm4_excel/export/configuration_sheet/configuration_sheet.py
usdm4_excel/export/excel_table_writer/__init__.py
usdm4_excel/export/excel_table_writer/excel_table_writer.py
usdm4_excel/export/study_activities_sheet/__init__.py
usdm4_excel/export/study_activities_sheet/activities_panel.py
usdm4_excel/export/study_activities_sheet/study_activities_sheet.py
usdm4_excel/export/study_arms_sheet/__init__.py
usdm4_excel/export/study_arms_sheet/arms_panel.py
usdm4_excel/export/study_arms_sheet/study_arms_sheet.py
usdm4_excel/export/study_design_sheet/__init__.py
usdm4_excel/export/study_design_sheet/high_level_design_panel.py
usdm4_excel/export/study_design_sheet/main_panel.py
usdm4_excel/export/study_design_sheet/study_design_sheet.py
usdm4_excel/export/study_document_content_sheet/__init__.py
usdm4_excel/export/study_document_content_sheet/document_content_panel.py
usdm4_excel/export/study_document_content_sheet/study_document_content_sheet.py
usdm4_excel/export/study_document_sheet/__init__.py
usdm4_excel/export/study_document_sheet/document_panel.py
usdm4_excel/export/study_document_sheet/study_document_sheet.py
usdm4_excel/export/study_encounters_sheet/__init__.py
usdm4_excel/export/study_encounters_sheet/encounters_panel.py
usdm4_excel/export/study_encounters_sheet/study_encounters_sheet.py
usdm4_excel/export/study_epochs_sheet/__init__.py
usdm4_excel/export/study_epochs_sheet/epochs_panel.py
usdm4_excel/export/study_epochs_sheet/study_epochs_sheet.py
usdm4_excel/export/study_identifiers_sheet/__init__.py
usdm4_excel-0.8.1.dist-info/licenses/LICENSE
usdm4_excel-0.8.1.dist-info/METADATA
usdm4_excel-0.8.1.dist-info/WHEEL
usdm4_excel-0.8.1.dist-info/top_level.txt
usdm4_excel-0.8.1.dist-info/RECORD
